prostruc/__init__.py
prostruc/alignment.py
prostruc/analyser.py
prostruc/app.py
prostruc/blast.py
prostruc/cif_pdb.py
prostruc/cleanup.py
prostruc/create_database.py
prostruc/deeplearning_prediction.py
prostruc/initial_checks.py
prostruc/metrics.py
prostruc/model.py
prostruc/target.py
prostruc/template.py
prostruc/validation.py
prostruc-0.0.2.dist-info/LICENSE.txt
prostruc-0.0.2.dist-info/METADATA
prostruc-0.0.2.dist-info/WHEEL
prostruc-0.0.2.dist-info/entry_points.txt
prostruc-0.0.2.dist-info/top_level.txt
prostruc-0.0.2.dist-info/RECORD
