Metadata-Version: 2.1
Name: prostruc
Version: 0.0.2
Summary: Prostruc: A Comprehensive Command-line Tool for Protein Structure Prediction and Validation
Home-page: https://github.com/omicscodeathon/prostruct
Author: The Prostruc Team
Author-email: senawilson123@gmail.com
License: MIT
Classifier: License :: OSI Approved :: MIT License
Classifier: Operating System :: OS Independent
Classifier: Programming Language :: Python :: 3
Classifier: Programming Language :: Python :: 3.8
Classifier: Programming Language :: Python :: 3.9
Classifier: Programming Language :: Python :: 3.10
Classifier: Development Status :: 5 - Production/Stable
Classifier: Intended Audience :: Developers
Requires-Python: >=3.6
License-File: LICENSE.txt
Requires-Dist: biopython (>=1.76)
Requires-Dist: docker (<5.0,>=3.0)
Requires-Dist: reportlab (<4.0,>=3.5)
